OddEvenChecker/__init__.py
OddEvenChecker/checker.py
oddevencheck-0.1.0.dist-info/METADATA
oddevencheck-0.1.0.dist-info/WHEEL
oddevencheck-0.1.0.dist-info/top_level.txt
oddevencheck-0.1.0.dist-info/RECORD
